gitsemver/__init__.py
gitsemver/config.py
gitsemver/index.py
gitsemver/parse.py
gitsemver/version.py
gitsemver-0.3.5.dist-info/entry_points.txt
gitsemver-0.3.5.dist-info/WHEEL
gitsemver-0.3.5.dist-info/METADATA
gitsemver-0.3.5.dist-info/RECORD
